selenium_browserkit/__init__.py
selenium_browserkit/browser.py
selenium_browserkit/node.py
selenium_browserkit/utils/__init__.py
selenium_browserkit/utils/browser_helper.py
selenium_browserkit/utils/core.py
selenium_browserkit-1.1.0.dist-info/licenses/LICENSE
selenium_browserkit-1.1.0.dist-info/METADATA
selenium_browserkit-1.1.0.dist-info/WHEEL
selenium_browserkit-1.1.0.dist-info/top_level.txt
selenium_browserkit-1.1.0.dist-info/RECORD
