Metadata-Version: 2.4
Name: selenium-browserkit
Version: 1.1.0
Summary: A toolkit for Selenium automation with multi-profile support
Author-email: Tran Lam <lam.tranledien@gmail.com>
License-Expression: MIT
Project-URL: Homepage, https://github.com/tranledienlam/selenium-browserkit
Project-URL: Issues, https://github.com/tranledienlam/selenium-browserkit/issues
Keywords: selenium,automation,browser,profile,toolkit
Requires-Python: >=3.8
License-File: LICENSE
Requires-Dist: selenium<5.0,>=4.38
Requires-Dist: requests<3.0,>=2.32
Requires-Dist: screeninfo<1.0,>=0.8
Requires-Dist: pillow>=12.0
Requires-Dist: google-genai<2.0,>=1.50
Requires-Dist: psutil<8.0,>=7.1
Dynamic: license-file
